referencing_http/__init__.py
referencing_http/tests/__init__.py
referencing_http/tests/test_integration.py
referencing_http-0.1.1.dist-info/METADATA
referencing_http-0.1.1.dist-info/WHEEL
referencing_http-0.1.1.dist-info/licenses/COPYING
referencing_http-0.1.1.dist-info/RECORD
